py_simple_inject-0.8.0.dist-info/METADATA
py_simple_inject-0.8.0.dist-info/WHEEL
py_simple_inject-0.8.0.dist-info/entry_points.txt
py_simple_inject-0.8.0.dist-info/licenses/LICENSE
simple_inject/__init__.py
simple_inject/core.py
py_simple_inject-0.8.0.dist-info/RECORD
