Metadata-Version: 2.1
Name: py-simple-inject
Version: 0.8.0
Summary: A lightweight dependency injection library for Python
Keywords: dependency injection,DI,IoC,inversion of control
Author-Email: frostime <frostime@foxmail.com>
License: MIT
Classifier: Development Status :: 4 - Beta
Classifier: Intended Audience :: Developers
Classifier: License :: OSI Approved :: MIT License
Classifier: Programming Language :: Python :: 3
Classifier: Programming Language :: Python :: 3.7
Classifier: Programming Language :: Python :: 3.8
Classifier: Programming Language :: Python :: 3.9
Classifier: Programming Language :: Python :: 3.10
Classifier: Programming Language :: Python :: 3.11
Classifier: Topic :: Software Development :: Libraries :: Python Modules
Project-URL: Homepage, https://github.com/frostime/simple-inject-py
Project-URL: Bug Tracker, https://github.com/frostime/simple-inject-py/issues
Requires-Python: >=3.8
